MANIFEST.in
README.rst
setup.cfg
setup.py
share/data/BIOGRID-PTM-15-3.1.93_SMALL.ptmtab.txt.gz
share/data/BIOGRID-PTM-RELATIONSHIPS-3.1.93.ptmrel.txt.gz
share/data/PKN-yeast.sif
share/data/PKN-yeastScaffold.sif
share/data/YEAST_TIC.csv
share/data/YEAST_annotations_all.pkl
share/data/YEAST_annotations_small.pkl
share/data/YEAST_raw_sample.csv
share/data/YEAST_small_all.csv
share/data/Yeast_all_raw.csv
share/data/alpha0.csv
share/data/alpha1.csv
share/data/alpha10.csv
share/data/alpha20.csv
share/data/alpha45.csv
share/data/alpha5.csv
src/msdas/__init__.py
src/msdas/alignment.py
src/msdas/annotations.py
src/msdas/clustering.py
src/msdas/main.py
src/msdas/multimidas.py
src/msdas/network.py
src/msdas/phosphogrid.py
src/msdas/psites.py
src/msdas/readers.py
src/msdas/replicates.py
src/msdas/tools.py
src/msdas/yeast.py
src/msdas.egg-info/PKG-INFO
src/msdas.egg-info/SOURCES.txt
src/msdas.egg-info/dependency_links.txt
src/msdas.egg-info/not-zip-safe
src/msdas.egg-info/requires.txt
src/msdas.egg-info/top_level.txt
test/test_alignment.py
test/test_annotations.py
test/test_clustering.py
test/test_network.py
test/test_phosphogrid.py
test/test_psites.py
test/test_readers.py
test/test_replicates.py
test/test_tools.py
test/test_yeast.py